Metadata-Version: 2.1
Name: DeepCache-shallow-onnx
Version: 0.1.3
Summary: DeepCache-shallow-onnx: Accelerating Diffusion Models for Free
Home-page: https://github.com/horseee/DeepCache-shallow-onnx
Author: Xinyin Ma
Author-email: maxinyin@u.nus.edu
Classifier: Programming Language :: Python :: 3
Classifier: License :: OSI Approved :: Apache Software License
Classifier: Operating System :: OS Independent
Requires-Python: >=3.6
License-File: LICENSE
Requires-Dist: torch
Requires-Dist: diffusers==0.24.0
Requires-Dist: transformers
Requires-Dist: huggingface-hub==0.25.2
